<?xml version="1.0" encoding="utf-8"?>
<!DOCTYPE hibernate-mapping PUBLIC "-//Hibernate/Hibernate Mapping DTD 3.0//EN"
"http://hibernate.sourceforge.net/hibernate-mapping-3.0.dtd">
<!-- 
    Mapping file autogenerated by MyEclipse Persistence Tools
-->
<hibernate-mapping>
    <class name="com.ems.entity.InfoPageResource" table="info_page_resource" catalog="protest">
        <id name="resourceId" type="java.lang.Integer">
            <column name="resource_id" />
            <generator class="assigned" />
        </id>
        <property name="pageResource" type="java.lang.String">
            <column name="page_resource" length="20" />
        </property>
        <property name="xtypeCode" type="java.lang.String">
            <column name="xtype_code" length="20" />
        </property>
        <property name="resourceTop" type="java.lang.Integer">
            <column name="resource_top" />
        </property>
        <property name="resourceLeft" type="java.lang.Integer">
            <column name="resource_left" />
        </property>
        <property name="resourceWidth" type="java.lang.Integer">
            <column name="resource_width" />
        </property>
        <property name="resourceHeight" type="java.lang.Integer">
            <column name="resource_height" />
        </property>
        <property name="valueId" type="java.lang.String">
            <column name="value_id" length="20" />
        </property>
        <property name="config" type="java.lang.String">
            <column name="config" />
        </property>
        <property name="baseCls" type="java.lang.String">
            <column name="base_cls" length="20" />
        </property>
    </class>
</hibernate-mapping>
